<?xml version="1.0" encoding="UTF-8"?>
<databaseChangeLog
        xmlns:xsi="http://www.w3.org/2001/XMLSchema-instance"
        xmlns:ext="http://www.liquibase.org/xml/ns/dbchangelog-ext"
        xmlns="http://www.liquibase.org/xml/ns/dbchangelog"
        xsi:schemaLocation="http://www.liquibase.org/xml/ns/dbchangelog http://www.liquibase.org/xml/ns/dbchangelog/dbchangelog-3.1.xsd
    http://www.liquibase.org/xml/ns/dbchangelog-ext http://www.liquibase.org/xml/ns/dbchangelog/dbchangelog-ext.xsd">
    <changeSet author="evgen_smirnov" id="3">
        <insert tableName="company">
            <column name="name" value="Luxoft"/>
        </insert>
        <insert tableName="company">
            <column name="name" value="Sberbank"/>
        </insert>
        <insert tableName="company">
            <column name="name" value="T-Systems"/>
        </insert>
        <insert tableName="company">
            <column name="name" value="Yandex"/>
        </insert>
        <insert tableName="company">
            <column name="name" value="Google"/>
        </insert>
        <insert tableName="company">
            <column name="name" value="Epam"/>
        </insert>
    </changeSet>
</databaseChangeLog>